{
  "minecraft:recipes/redstone/lever": {
    "criteria": {
      "has_cobblestone": "2021-02-16 04:48:02 +1300"
    },
    "done": true
  },
  "minecraft:recipes/building_blocks/granite_stairs": {
    "criteria": {
      "has_granite": "2021-02-16 04:48:16 +1300"
    },
    "done": true
  },
  "minecraft:recipes/building_blocks/cobblestone_stairs_from_cobblestone_stonecutting": {
    "criteria": {
      "has_cobblestone": "2021-02-16 04:48:02 +1300"
    },
    "done": true
  },
  "minecraft:recipes/tools/compass": {
    "criteria": {
      "has_redstone": "2021-02-16 04:48:07 +1300"
    },
    "done": true
  },
  "minecraft:recipes/building_blocks/andesite_stairs_from_andesite_stonecutting": {
    "criteria": {
      "has_andesite": "2021-02-16 04:48:13 +1300"
    },
    "done": true
  },
  "minecraft:recipes/decorations/diorite_wall_from_diorite_stonecutting": {
    "criteria": {
      "has_diorite": "2021-02-16 16:38:45 +1300"
    },
    "done": true
  },
  "minecraft:recipes/misc/iron_ingot": {
    "criteria": {
      "has_iron_ore": "2021-02-16 16:38:45 +1300"
    },
    "done": true
  },
  "minecraft:recipes/decorations/diorite_wall": {
    "criteria": {
      "has_diorite": "2021-02-16 16:38:45 +1300"
    },
    "done": true
  },
  "minecraft:recipes/combat/diamond_chestplate": {
    "criteria": {
      "has_diamond": "2021-02-16 16:38:45 +1300"
    },
    "done": true
  },
  "minecraft:recipes/building_blocks/polished_andesite_stairs_from_andesite_stonecutting": {
    "criteria": {
      "has_andesite": "2021-02-16 04:48:13 +1300"
    },
    "done": true
  },
  "minecraft:story/mine_stone": {
    "criteria": {
      "get_stone": "2021-02-16 04:48:02 +1300"
    },
    "done": true
  },
  "minecraft:recipes/building_blocks/stone": {
    "criteria": {
      "has_cobblestone": "2021-02-16 04:48:02 +1300"
    },
    "done": true
  },
  "minecraft:recipes/building_blocks/polished_andesite": {
    "criteria": {
      "has_stone": "2021-02-16 04:48:13 +1300"
    },
    "done": true
  },
  "minecraft:recipes/tools/diamond_axe": {
    "criteria": {
      "has_diamond": "2021-02-16 16:38:45 +1300"
    },
    "done": true
  },
  "minecraft:recipes/redstone/target": {
    "criteria": {
      "has_redstone": "2021-02-16 04:48:07 +1300"
    },
    "done": true
  },
  "minecraft:recipes/decorations/furnace": {
    "criteria": {
      "has_cobblestone": "2021-02-16 04:48:02 +1300"
    },
    "done": true
  },
  "minecraft:recipes/building_blocks/diorite_stairs_from_diorite_stonecutting": {
    "criteria": {
      "has_diorite": "2021-02-16 16:38:45 +1300"
    },
    "done": true
  },
  "minecraft:adventure/adventuring_time": {
    "criteria": {
      "minecraft:forest": "2021-02-16 04:47:13 +1300",
      "minecraft:plains": "2021-02-16 04:46:40 +1300"
    },
    "done": false
  },
  "minecraft:recipes/combat/diamond_leggings": {
    "criteria": {
      "has_diamond": "2021-02-16 16:38:45 +1300"
    },
    "done": true
  },
  "minecraft:recipes/building_blocks/andesite_stairs": {
    "criteria": {
      "has_andesite": "2021-02-16 04:48:13 +1300"
    },
    "done": true
  },
  "minecraft:recipes/decorations/campfire": {
    "criteria": {
      "has_coal": "2021-02-16 16:38:45 +1300"
    },
    "done": true
  },
  "minecraft:recipes/building_blocks/diorite_slab_from_diorite_stonecutting": {
    "criteria": {
      "has_diorite": "2021-02-16 16:38:45 +1300"
    },
    "done": true
  },
  "minecraft:recipes/building_blocks/cobblestone_slab_from_cobblestone_stonecutting": {
    "criteria": {
      "has_cobblestone": "2021-02-16 04:48:02 +1300"
    },
    "done": true
  },
  "minecraft:recipes/redstone/redstone_torch": {
    "criteria": {
      "has_redstone": "2021-02-16 04:48:07 +1300"
    },
    "done": true
  },
  "minecraft:recipes/decorations/chest": {
    "criteria": {
      "has_lots_of_items": "2021-02-16 16:38:45 +1300"
    },
    "done": true
  },
  "minecraft:recipes/transportation/birch_boat": {
    "criteria": {
      "in_water": "2021-02-16 16:38:49 +1300"
    },
    "done": true
  },
  "minecraft:recipes/combat/stone_sword": {
    "criteria": {
      "has_cobblestone": "2021-02-16 04:48:02 +1300"
    },
    "done": true
  },
  "minecraft:recipes/decorations/cobblestone_wall": {
    "criteria": {
      "has_cobblestone": "2021-02-16 04:48:02 +1300"
    },
    "done": true
  },
  "minecraft:recipes/building_blocks/polished_andesite_slab_from_andesite_stonecutting": {
    "criteria": {
      "has_andesite": "2021-02-16 04:48:13 +1300"
    },
    "done": true
  },
  "minecraft:recipes/building_blocks/polished_granite_slab_from_granite_stonecutting": {
    "criteria": {
      "has_granite": "2021-02-16 04:48:16 +1300"
    },
    "done": true
  },
  "minecraft:recipes/building_blocks/polished_andesite_from_andesite_stonecutting": {
    "criteria": {
      "has_andesite": "2021-02-16 04:48:13 +1300"
    },
    "done": true
  },
  "minecraft:recipes/misc/gold_ingot_from_blasting": {
    "criteria": {
      "has_gold_ore": "2021-02-16 16:38:47 +1300"
    },
    "done": true
  },
  "minecraft:recipes/transportation/acacia_boat": {
    "criteria": {
      "in_water": "2021-02-16 16:38:49 +1300"
    },
    "done": true
  },
  "minecraft:recipes/tools/stone_pickaxe": {
    "criteria": {
      "has_cobblestone": "2021-02-16 04:48:02 +1300"
    },
    "done": true
  },
  "minecraft:recipes/combat/diamond_sword": {
    "criteria": {
      "has_diamond": "2021-02-16 16:38:45 +1300"
    },
    "done": true
  },
  "minecraft:recipes/building_blocks/andesite_slab_from_andesite_stonecutting": {
    "criteria": {
      "has_andesite": "2021-02-16 04:48:13 +1300"
    },
    "done": true
  },
  "minecraft:recipes/building_blocks/coal_block": {
    "criteria": {
      "has_coal": "2021-02-16 16:38:45 +1300"
    },
    "done": true
  },
  "minecraft:recipes/transportation/jungle_boat": {
    "criteria": {
      "in_water": "2021-02-16 16:38:49 +1300"
    },
    "done": true
  },
  "minecraft:recipes/misc/iron_ingot_from_blasting": {
    "criteria": {
      "has_iron_ore": "2021-02-16 16:38:45 +1300"
    },
    "done": true
  },
  "minecraft:recipes/misc/gold_ingot": {
    "criteria": {
      "has_gold_ore": "2021-02-16 16:38:47 +1300"
    },
    "done": true
  },
  "minecraft:recipes/decorations/cobblestone_wall_from_cobblestone_stonecutting": {
    "criteria": {
      "has_cobblestone": "2021-02-16 04:48:02 +1300"
    },
    "done": true
  },
  "minecraft:recipes/decorations/jukebox": {
    "criteria": {
      "has_diamond": "2021-02-16 16:38:45 +1300"
    },
    "done": true
  },
  "minecraft:recipes/transportation/spruce_boat": {
    "criteria": {
      "in_water": "2021-02-16 16:38:49 +1300"
    },
    "done": true
  },
  "minecraft:recipes/tools/stone_shovel": {
    "criteria": {
      "has_cobblestone": "2021-02-16 04:48:02 +1300"
    },
    "done": true
  },
  "minecraft:recipes/building_blocks/diamond_block": {
    "criteria": {
      "has_diamond": "2021-02-16 16:38:45 +1300"
    },
    "done": true
  },
  "minecraft:recipes/tools/stone_hoe": {
    "criteria": {
      "has_cobblestone": "2021-02-16 04:48:02 +1300"
    },
    "done": true
  },
  "minecraft:recipes/tools/clock": {
    "criteria": {
      "has_redstone": "2021-02-16 04:48:07 +1300"
    },
    "done": true
  },
  "minecraft:recipes/transportation/dark_oak_boat": {
    "criteria": {
      "in_water": "2021-02-16 16:38:49 +1300"
    },
    "done": true
  },
  "minecraft:recipes/tools/diamond_pickaxe": {
    "criteria": {
      "has_diamond": "2021-02-16 16:38:45 +1300"
    },
    "done": true
  },
  "minecraft:recipes/tools/diamond_hoe": {
    "criteria": {
      "has_diamond": "2021-02-16 16:38:45 +1300"
    },
    "done": true
  },
  "minecraft:recipes/decorations/andesite_wall_from_andesite_stonecutting": {
    "criteria": {
      "has_andesite": "2021-02-16 04:48:13 +1300"
    },
    "done": true
  },
  "minecraft:recipes/building_blocks/diorite_stairs": {
    "criteria": {
      "has_diorite": "2021-02-16 16:38:45 +1300"
    },
    "done": true
  },
  "minecraft:recipes/building_blocks/granite_slab_from_granite_stonecutting": {
    "criteria": {
      "has_granite": "2021-02-16 04:48:16 +1300"
    },
    "done": true
  },
  "minecraft:recipes/tools/diamond_shovel": {
    "criteria": {
      "has_diamond": "2021-02-16 16:38:45 +1300"
    },
    "done": true
  },
  "minecraft:recipes/building_blocks/polished_granite_from_granite_stonecutting": {
    "criteria": {
      "has_granite": "2021-02-16 04:48:16 +1300"
    },
    "done": true
  },
  "minecraft:recipes/redstone/redstone_block": {
    "criteria": {
      "has_redstone": "2021-02-16 04:48:07 +1300"
    },
    "done": true
  },
  "minecraft:recipes/building_blocks/polished_granite": {
    "criteria": {
      "has_stone": "2021-02-16 04:48:16 +1300"
    },
    "done": true
  },
  "minecraft:recipes/building_blocks/granite_slab": {
    "criteria": {
      "has_granite": "2021-02-16 04:48:16 +1300"
    },
    "done": true
  },
  "minecraft:recipes/building_blocks/andesite": {
    "criteria": {
      "has_stone": "2021-02-16 16:38:45 +1300"
    },
    "done": true
  },
  "minecraft:recipes/redstone/piston": {
    "criteria": {
      "has_redstone": "2021-02-16 04:48:07 +1300"
    },
    "done": true
  },
  "minecraft:recipes/building_blocks/cobblestone_slab": {
    "criteria": {
      "has_cobblestone": "2021-02-16 04:48:02 +1300"
    },
    "done": true
  },
  "minecraft:recipes/building_blocks/cobblestone_stairs": {
    "criteria": {
      "has_cobblestone": "2021-02-16 04:48:02 +1300"
    },
    "done": true
  },
  "minecraft:recipes/building_blocks/diorite_slab": {
    "criteria": {
      "has_diorite": "2021-02-16 16:38:45 +1300"
    },
    "done": true
  },
  "minecraft:recipes/decorations/granite_wall_from_granite_stonecutting": {
    "criteria": {
      "has_granite": "2021-02-16 04:48:16 +1300"
    },
    "done": true
  },
  "minecraft:recipes/decorations/granite_wall": {
    "criteria": {
      "has_granite": "2021-02-16 04:48:16 +1300"
    },
    "done": true
  },
  "minecraft:recipes/redstone/note_block": {
    "criteria": {
      "has_redstone": "2021-02-16 04:48:07 +1300"
    },
    "done": true
  },
  "minecraft:recipes/combat/diamond_boots": {
    "criteria": {
      "has_diamond": "2021-02-16 16:38:45 +1300"
    },
    "done": true
  },
  "minecraft:story/mine_diamond": {
    "criteria": {
      "diamond": "2021-02-16 16:38:45 +1300"
    },
    "done": true
  },
  "minecraft:recipes/building_blocks/polished_diorite": {
    "criteria": {
      "has_stone": "2021-02-16 16:38:45 +1300"
    },
    "done": true
  },
  "minecraft:recipes/decorations/andesite_wall": {
    "criteria": {
      "has_andesite": "2021-02-16 04:48:13 +1300"
    },
    "done": true
  },
  "minecraft:recipes/building_blocks/polished_granite_stairs_from_granite_stonecutting": {
    "criteria": {
      "has_granite": "2021-02-16 04:48:16 +1300"
    },
    "done": true
  },
  "minecraft:recipes/combat/diamond_helmet": {
    "criteria": {
      "has_diamond": "2021-02-16 16:38:45 +1300"
    },
    "done": true
  },
  "minecraft:recipes/building_blocks/andesite_slab": {
    "criteria": {
      "has_andesite": "2021-02-16 04:48:13 +1300"
    },
    "done": true
  },
  "minecraft:recipes/redstone/dropper": {
    "criteria": {
      "has_redstone": "2021-02-16 04:48:07 +1300"
    },
    "done": true
  },
  "minecraft:recipes/transportation/oak_boat": {
    "criteria": {
      "in_water": "2021-02-16 16:38:49 +1300"
    },
    "done": true
  },
  "minecraft:recipes/tools/stone_axe": {
    "criteria": {
      "has_cobblestone": "2021-02-16 04:48:02 +1300"
    },
    "done": true
  },
  "minecraft:recipes/building_blocks/granite_stairs_from_granite_stonecutting": {
    "criteria": {
      "has_granite": "2021-02-16 04:48:16 +1300"
    },
    "done": true
  },
  "minecraft:recipes/building_blocks/polished_diorite_from_diorite_stonecutting": {
    "criteria": {
      "has_diorite": "2021-02-16 16:38:45 +1300"
    },
    "done": true
  },
  "DataVersion": 2586
}