{
  "minecraft:recipes/misc/diamond_from_blasting": {
    "criteria": {
      "has_diamond_ore": "2021-02-16 19:30:40 +1300"
    },
    "done": true
  },
  "minecraft:recipes/misc/diamond_from_smelting": {
    "criteria": {
      "has_diamond_ore": "2021-02-16 19:30:40 +1300"
    },
    "done": true
  },
  "minecraft:adventure/adventuring_time": {
    "criteria": {
      "minecraft:forest": "2021-02-16 19:27:29 +1300",
      "minecraft:taiga": "2021-02-16 19:26:39 +1300",
      "minecraft:taiga_hills": "2021-02-16 19:27:17 +1300",
      "minecraft:plains": "2021-02-16 19:27:29 +1300"
    },
    "done": false
  },
  "DataVersion": 2586
}